invisibleroads_macros_web/__init__.py
invisibleroads_macros_web/browser.py
invisibleroads_macros_web/escape.py
invisibleroads_macros_web/jinja.py
invisibleroads_macros_web/markdown.py
invisibleroads_macros_web/port.py
invisibleroads_macros_web/starlette.py
tests/__init__.py
tests/test_escape.py
tests/test_markdown.py
tests/test_port.py
invisibleroads_macros_web-0.3.7.dist-info/METADATA
invisibleroads_macros_web-0.3.7.dist-info/WHEEL
invisibleroads_macros_web-0.3.7.dist-info/top_level.txt
invisibleroads_macros_web-0.3.7.dist-info/zip-safe
invisibleroads_macros_web-0.3.7.dist-info/RECORD
