Metadata-Version: 2.1
Name: invisibleroads-macros-web
Version: 0.3.7
Summary: Shortcut functions for web operations
Home-page: https://github.com/invisibleroads/invisibleroads-macros-web
Author: Roy Hyunjin Han
Author-email: rhh@crosscompute.com
Keywords: invisibleroads
Classifier: Programming Language :: Python
Classifier: License :: OSI Approved :: MIT License
Requires-Dist: invisibleroads-macros-disk >=1.3.0
Requires-Dist: invisibleroads-macros-process >=0.2.0
Provides-Extra: jinja
Requires-Dist: jinja2 ; extra == 'jinja'
Provides-Extra: markdown
Requires-Dist: markdown2[all] ; extra == 'markdown'
Provides-Extra: starlette
Requires-Dist: starlette ; extra == 'starlette'
Provides-Extra: test
Requires-Dist: pytest ; extra == 'test'
Requires-Dist: pytest-cov ; extra == 'test'
